serverless_thrift/__init__.py
serverless_thrift/server/TFunctionServer.py
serverless_thrift/server/TLambdaServer.py
serverless_thrift/server/__init__.py
serverless_thrift/transport/TLambda.py
serverless_thrift/transport/__init__.py
test/server/__init__.py
test/server/conftest.py
test/server/test_TFunctionServer.py
test/server/test_TLambdaServer.py
test/transport/__init__.py
test/transport/test_TLambda.py
serverless_thrift-1.3.0.dist-info/METADATA
serverless_thrift-1.3.0.dist-info/WHEEL
serverless_thrift-1.3.0.dist-info/top_level.txt
serverless_thrift-1.3.0.dist-info/RECORD
