Metadata-Version: 2.1
Name: serverless-thrift
Version: 1.3.0
Summary: Run Thrift server and client on serverless functions
Home-page: https://github.com/galbash/serverless-rpc
Author: Gal Bashan & Tal Vintrob
Author-email: galbashan1@gmail.com
License: MIT
Keywords: serverless,lambda,aws-lambda,rpc,thrift
Platform: UNKNOWN
Classifier: Intended Audience :: Developers
Classifier: Operating System :: OS Independent
Classifier: Programming Language :: Python
Classifier: Topic :: Software Development :: Libraries
Classifier: Topic :: Software Development :: Libraries :: Python Modules
Requires-Dist: boto3 (>=1.9.198)
Requires-Dist: thrift (>=0.11.0)
